similaritymeasures/__init__.py
similaritymeasures/similaritymeasures.py
similaritymeasures/version.py
similaritymeasures-1.4.0.dist-info/licenses/LICENSE
similaritymeasures-1.4.0.dist-info/METADATA
similaritymeasures-1.4.0.dist-info/WHEEL
similaritymeasures-1.4.0.dist-info/top_level.txt
similaritymeasures-1.4.0.dist-info/RECORD
