Metadata-Version: 2.4
Name: similaritymeasures
Version: 1.4.0
Summary: Quantify the difference between two arbitrary curves in space
Author-email: Charles Jekel <cjekel@gmail.com>
License-Expression: MIT
Project-URL: Homepage, https://github.com/cjekel/similarity_measures
Project-URL: Repository, https://github.com/cjekel/similarity_measures
Project-URL: Documentation, https://jekel.me/similarity_measures/index.html
Project-URL: Issues, https://github.com/cjekel/similarity_measures/issues
Classifier: Development Status :: 5 - Production/Stable
Classifier: Intended Audience :: Developers
Classifier: Intended Audience :: Science/Research
Classifier: Programming Language :: Python :: 3
Classifier: Topic :: Scientific/Engineering
Classifier: Topic :: Scientific/Engineering :: Mathematics
Requires-Python: >=3.8
License-File: LICENSE
Requires-Dist: numpy>=1.14.0
Requires-Dist: scipy>=0.19.0
Dynamic: license-file
